querylizer/__init__.py
querylizer/analyzers.py
querylizer/apps.py
querylizer/instrumentation.py
querylizer/loggers.py
querylizer/middleware.py
querylizer/settings.py
django_querylizer-0.1.0.dist-info/METADATA
django_querylizer-0.1.0.dist-info/WHEEL
django_querylizer-0.1.0.dist-info/licenses/LICENSE
django_querylizer-0.1.0.dist-info/RECORD
