Metadata-Version: 2.4
Name: django-querylizer
Version: 0.1.0
Summary: Automatic Django query performance analyzer and logger
Project-URL: Homepage, https://github.com/AvicennaJr/django-querylizer
Project-URL: Repository, https://github.com/AvicennaJr/django-querylizer
Project-URL: Documentation, https://github.com/AvicennaJr/django-querylizer#readme
Project-URL: Bug Tracker, https://github.com/AvicennaJr/django-querylizer/issues
Author-email: Fuad Habib <fuad@subcode.africa>
License-Expression: MIT
License-File: LICENSE
Keywords: analyzer,database,django,monitoring,optimization,orm,performance,query
Classifier: Development Status :: 4 - Beta
Classifier: Framework :: Django
Classifier: Intended Audience :: Developers
Classifier: License :: OSI Approved :: MIT License
Classifier: Operating System :: OS Independent
Classifier: Programming Language :: Python :: 3.8
Classifier: Programming Language :: Python :: 3.9
Classifier: Programming Language :: Python :: 3.10
Classifier: Programming Language :: Python :: 3.11
Classifier: Programming Language :: Python :: 3.12
Classifier: Topic :: Database
Classifier: Topic :: Software Development :: Libraries :: Python Modules
Classifier: Topic :: System :: Monitoring
Classifier: Typing :: Typed
Requires-Python: >=3.8
Requires-Dist: django>=3.2
Provides-Extra: dev
Requires-Dist: black>=23.0.0; extra == 'dev'
Requires-Dist: django-stubs>=4.2.0; extra == 'dev'
Requires-Dist: mypy>=1.0.0; extra == 'dev'
Requires-Dist: ruff>=0.1.0; extra == 'dev'
